humboldt.cmfbibliographyat-0.2.5.3-nspkg.pth
humboldt.cmfbibliographyat-0.2.5.3.dist-info/WHEEL
humboldt.cmfbibliographyat-0.2.5.3.dist-info/metadata.json
humboldt.cmfbibliographyat-0.2.5.3.dist-info/RECORD
humboldt.cmfbibliographyat-0.2.5.3.dist-info/top_level.txt
humboldt.cmfbibliographyat-0.2.5.3.dist-info/DESCRIPTION.rst
humboldt.cmfbibliographyat-0.2.5.3.dist-info/namespace_packages.txt
humboldt.cmfbibliographyat-0.2.5.3.dist-info/paster_plugins.txt
humboldt.cmfbibliographyat-0.2.5.3.dist-info/METADATA
humboldt.cmfbibliographyat-0.2.5.3.dist-info/entry_points.txt
humboldt/cmfbibliographyat/patches.py
humboldt/cmfbibliographyat/configure.zcml
humboldt/cmfbibliographyat/README.txt
humboldt/cmfbibliographyat/patches.zcml
humboldt/cmfbibliographyat/__init__.py
humboldt/cmfbibliographyat/overrides.zcml
humboldt/cmfbibliographyat/interfaces.py
humboldt/cmfbibliographyat/setuphandlers.py
humboldt/cmfbibliographyat/bibliographicitemextensions.py
humboldt/cmfbibliographyat/skins.zcml
humboldt/cmfbibliographyat/header.txt
humboldt/cmfbibliographyat/config.py
humboldt/cmfbibliographyat/adapters/configure.zcml
humboldt/cmfbibliographyat/adapters/adapters.py
humboldt/cmfbibliographyat/adapters/__init__.py
humboldt/cmfbibliographyat/tests/test_doctest.py
humboldt/cmfbibliographyat/tests/base.py
humboldt/cmfbibliographyat/tests/__init__.py
humboldt/cmfbibliographyat/profiles/default/viewlets.xml
humboldt/cmfbibliographyat/profiles/default/actions.xml
humboldt/cmfbibliographyat/profiles/default/humboldt.cmfbibliographyat_various.txt
humboldt/cmfbibliographyat/profiles/default/metadata.xml
humboldt/cmfbibliographyat/profiles/default/import_steps.xml
humboldt/cmfbibliographyat/profiles/default/workflows.xml
humboldt/cmfbibliographyat/profiles/default/factorytool.xml
humboldt/cmfbibliographyat/profiles/default/skins.xml
humboldt/cmfbibliographyat/profiles/default/types.xml
humboldt/cmfbibliographyat/profiles/default/portlets.xml
humboldt/cmfbibliographyat/profiles/default/browserlayer.xml
humboldt/cmfbibliographyat/profiles/default/types/InbookReference.xml
humboldt/cmfbibliographyat/profiles/default/types/ConferenceReference.xml
humboldt/cmfbibliographyat/profiles/default/types/WebpublishedReference.xml
humboldt/cmfbibliographyat/profiles/default/types/ArticleReference.xml
humboldt/cmfbibliographyat/profiles/default/types/PreprintReference.xml
humboldt/cmfbibliographyat/profiles/default/types/InproceedingsReference.xml
