Metadata-Version: 2.0
Name: humboldt.cmfbibliographyat
Version: 0.2.5.3
Summary: Humboldt University CMFBibliographyAT extensions
Home-page: http://pypi.python.org/pypi/humboldt.cmfbibliographyat
Author: Andreas Jung
Author-email: info@zopyx.com
License: GPL
Keywords: Plone CMFBibliographyAT Bibliographies Zope
Platform: UNKNOWN
Classifier: Framework :: Plone
Classifier: Intended Audience :: Developers
Classifier: License :: OSI Approved :: GNU General Public License (GPL)
Requires-Dist: setuptools
Requires-Dist: collective.monkeypatcher
Requires-Dist: collective.monkeypatcherpanel
Requires-Dist: Products.basesyndication
Requires-Dist: Products.fatsyndication
Requires-Dist: Products.CMFBibliographyAT
Provides-Extra: tests
Requires-Dist: zope.testing; extra == 'tests'
